blablabla_api/__init__.py
blablabla_api/error.py
blablabla_api/domains/__init__.py
blablabla_api/domains/address_book/__init__.py
blablabla_api/domains/advanced_account/__init__.py
blablabla_api/domains/auto_swaps/__init__.py
blablabla_api/domains/basic_actions/__init__.py
blablabla_api/domains/blockchain_addresses/__init__.py
blablabla_api/domains/crosschain_bridge/__init__.py
blablabla_api/domains/crosschain_swaps/__init__.py
blablabla_api/domains/invoices/__init__.py
blablabla_api/domains/kyt/__init__.py
blablabla_api/domains/orders/__init__.py
blablabla_api/domains/orphan_transactions/__init__.py
blablabla_api/domains/partners_api/__init__.py
blablabla_api/domains/personal_addresses/__init__.py
blablabla_api/domains/recurring_payments/__init__.py
blablabla_api/domains/webhooks/__init__.py
blablabla_api/domains/withdraws/__init__.py
blablabla_api/resources/__init__.py
blablabla_api/resources/constants.py
blablabla_api/resources/requester.py
blablabla_api/resources/response.py
blablabla_api/resources/utils.py
blablabla_api-0.0.4.dist-info/LICENSE
blablabla_api-0.0.4.dist-info/METADATA
blablabla_api-0.0.4.dist-info/WHEEL
blablabla_api-0.0.4.dist-info/top_level.txt
blablabla_api-0.0.4.dist-info/RECORD
