Metadata-Version: 2.1
Name: blablabla-api
Version: 0.0.4
Summary: SDK for Blablabla API
Home-page: https://github.com/blablabla/python_sdk
Author: Blablabla Team
Author-email: support@blablabla.io
License: UNKNOWN
Project-URL: Bug Tracker, https://github.com/blablabla/python_sdk/issues
Platform: UNKNOWN
Classifier: Programming Language :: Python :: 3
Classifier: License :: OSI Approved :: BSD License
Classifier: Operating System :: OS Independent
Requires-Python: >=3.6
License-File: LICENSE
Requires-Dist: requests >=2.28.0
